oyeahz_base/__init__.py
oyeahz_base/database/database_utils.py
oyeahz_base/logger/xlogger.py
oyeahz_base/model/base_model.py
oyeahz_base/redis/redis_utils.py
oyeahz_base/utils/network_utils.py
oyeahz_base/utils/oyeahz_utils.py
oyeahz_base-0.0.11.dist-info/METADATA
oyeahz_base-0.0.11.dist-info/WHEEL
oyeahz_base-0.0.11.dist-info/top_level.txt
oyeahz_base-0.0.11.dist-info/RECORD
