Metadata-Version: 2.1
Name: oyeahz-base
Version: 0.0.11
Summary: Oyeahz基础组件包
Home-page: https://github.com/dGhpcyBpcyBteSB3b3JsZA/oyeahz_base.git
Author: linan890107
Author-email: linan890107@126.com
License: UNKNOWN
Project-URL: Bug Tracker, https://github.com/dGhpcyBpcyBteSB3b3JsZA/oyeahz_base/issues
Platform: UNKNOWN
Classifier: Programming Language :: Python :: 3
Classifier: License :: OSI Approved :: MIT License
Classifier: Operating System :: OS Independent
Requires-Python: >=3.6
